LICENSE.txt
setup.py
AFRITON.egg-info/PKG-INFO
AFRITON.egg-info/SOURCES.txt
AFRITON.egg-info/dependency_links.txt
AFRITON.egg-info/top_level.txt
name_afrit/AFRI.py
name_afrit/Arg.py
name_afrit/OS.py
name_afrit/S_X.py
name_afrit/Taiwn.py
name_afrit/__init__.py